queuing/__init__.py
queuing/queuing.py
queuing-0.3.1.dist-info/LICENSE
queuing-0.3.1.dist-info/METADATA
queuing-0.3.1.dist-info/WHEEL
queuing-0.3.1.dist-info/top_level.txt
queuing-0.3.1.dist-info/RECORD
